tkconfigeditor/LICENSE
tkconfigeditor/README.MD
tkconfigeditor/__init__.py
tkconfigeditor/requirements.txt
tkconfigeditor/thirdparty.json
tkconfigeditor-0.12.dist-info/LICENSE.rst
tkconfigeditor-0.12.dist-info/METADATA
tkconfigeditor-0.12.dist-info/WHEEL
tkconfigeditor-0.12.dist-info/top_level.txt
tkconfigeditor-0.12.dist-info/RECORD
